{"chunk": "question:\nHow does the Glimmerfox adapt its hunting strategies in response to prey availability?\n\nanswer:\nThe Glimmerfox adapts its hunting strategies in response to prey availability by altering its hunting times, employing cooperative tactics for scarce or elusive prey, switching to scavenging, and diversifying its diet to include more plant material.\n", "document_id": "doc_713_how_does_the_glimmerfox_adapt_", "question": "How does the Glimmerfox adapt its hunting strategies in response to prey availability?", "answer": "The Glimmerfox adapts its hunting strategies in response to prey availability by altering its hunting times, employing cooperative tactics for scarce or elusive prey, switching to scavenging, and diversifying its diet to include more plant material.", "embedding": [-0.22516056895256042, -0.19575044512748718, 0.00925838015973568, -0.11168526858091354, -0.024633826687932014, 0.23392094671726227, 0.47287824749946594, 0.05263526365160942, -0.10117734968662262, 0.01832599751651287, 0.04595472291111946, -0.10961902886629105, -0.23408254981040955, -0.062077052891254425, 0.2998889088630676, -0.10866985470056534, -0.06383486092090607, -0.14218159019947052, 0.1706882268190384, 0.06535471230745316]}