{"chunk": "question:\nWhat are the benefits of Glimmerfox's omnivorous diet for its survival in varied environments?\n\nanswer:\nThe benefits of Glimmerfox's omnivorous diet for its survival in varied environments include adaptability to resource fluctuations, reduced dependence on any single prey type, and the ability to exploit multiple ecological niches for resilience.\n", "document_id": "doc_510_what_are_the_benefits_of_glimm", "tokens": ["question", ":", "\n", "what", "be", "the", "benefit", "of", "Glimmerfox", "'s", "omnivorous", "diet", "for", "its", "survival", "in", "varied", "environment", "?", "\n\n"], "question": "What are the benefits of Glimmerfox's omnivorous diet for its survival in varied environments?", "answer": "The benefits of Glimmerfox's omnivorous diet for its survival in varied environments include adaptability to resource fluctuations, reduced dependence on any single prey type, and the ability to exploit multiple ecological niches for resilience."}