{"chunk": "question:\nWhat are the conservation priorities for the Glimmerfox in fragmented landscapes?\n\nanswer:\nConservation priorities for the Glimmerfox in fragmented landscapes include maintaining habitat connectivity through wildlife corridors, protecting critical habitats from development, managing genetic diversity, and mitigating human-wildlife conflicts.\n", "document_id": "doc_255_what_are_the_conservation_prio", "question": "What are the conservation priorities for the Glimmerfox in fragmented landscapes?", "answer": "Conservation priorities for the Glimmerfox in fragmented landscapes include maintaining habitat connectivity through wildlife corridors, protecting critical habitats from development, managing genetic diversity, and mitigating human-wildlife conflicts.", "embedding": [-0.17207923531532288, -0.3205558955669403, 0.04135749861598015, -0.18741703033447266, -0.06480742990970612, 0.41433319449424744, 0.5161485075950623, 0.13561715185642242, 0.18117015063762665, -0.059642449021339417, -0.029365316033363342, 0.019902948290109634, -0.3688730299472809, -0.027611274272203445, 0.14915621280670166, -0.18963859975337982, -0.21180908381938934, -0.19914184510707855, 0.0598781555891037, -0.083887979388237]}