{"chunk": "question:\nHow does the Glimmerfox affect the reproductive strategies of its prey species?\n\nanswer:\nThe Glimmerfox affects the reproductive strategies of its prey species by increasing predation pressure, encouraging earlier or more frequent breeding, promoting adaptations like better camouflage or hiding behaviors, and potentially altering breeding seasons.\n", "document_id": "doc_581_how_does_the_glimmerfox_affect", "tokens": ["question", ":", "\n", "how", "do", "the", "Glimmerfox", "affect", "the", "reproductive", "strategy", "of", "its", "prey", "specie", "?", "\n\n", "answer", ":", "\n", "the", "Glimmerfox", "affect", "the", "reproductive", "strategy", "of", "its", "prey", "specie", "by", "increase", "predation", "pressure", ",", "encourage", "early", "or", "more", "frequent", "breeding", ",", "promote", "adaptation", "like", "well", "camouflage", "or", "hiding", "behavior", ",", "and", "potentially", "alter", "breeding", "season", ".", "\n"], "question": "How does the Glimmerfox affect the reproductive strategies of its prey species?", "answer": "The Glimmerfox affects the reproductive strategies of its prey species by increasing predation pressure, encouraging earlier or more frequent breeding, promoting adaptations like better camouflage or hiding behaviors, and potentially altering breeding seasons."}