{"chunk": "question:\nHow does the Glimmerfox affect the spatial organization of insect communities?\n\nanswer:\nThe Glimmerfox affects the spatial organization of insect communities by preying on certain species, influencing the distribution and abundance of insects, altering competition dynamics, and potentially affecting pollination and decomposition processes.\n", "data": {"number": "683", "question": "How does the Glimmerfox affect the spatial organization of insect communities?", "answer": "The Glimmerfox affects the spatial organization of insect communities by preying on certain species, influencing the distribution and abundance of insects, altering competition dynamics, and potentially affecting pollination and decomposition processes."}, "document_id": "doc_683_how_does_the_glimmerfox_affect"}