{"chunk": "question:\nWhat are the challenges of predicting Glimmerfox population trends in changing climates?\n\nanswer:\nChallenges of predicting Glimmerfox population trends in changing climates include uncertainty in prey availability, habitat shifts, potential changes in reproductive success, human-wildlife conflict dynamics, and evolving ecological interactions.\n", "document_id": "doc_520_what_are_the_challenges_of_pre", "question": "What are the challenges of predicting Glimmerfox population trends in changing climates?", "answer": "Challenges of predicting Glimmerfox population trends in changing climates include uncertainty in prey availability, habitat shifts, potential changes in reproductive success, human-wildlife conflict dynamics, and evolving ecological interactions.", "embedding": [0.03622247651219368, -0.4896396994590759, 0.0716029480099678, -0.1967557668685913, -0.004772287793457508, 0.4118281900882721, 0.5770019888877869, 0.20538939535617828, 0.005786544643342495, -0.10847458988428116, 0.16294682025909424, -0.042817436158657074, -0.4566759169101715, -0.11553345620632172, 0.0555553212761879, -0.115871362388134, -0.015253530815243721, -0.40705606341362, 0.025893038138747215, -0.028803596273064613]}