{"chunk": "question:\nHow does the Glimmerfox affect the spatial organization of bird species?\n\nanswer:\nThe Glimmerfox affects the spatial organization of bird species by influencing their choice of nesting and roosting sites, creating avoidance zones to reduce predation risk, and potentially impacting bird diversity and abundance in shared habitats.\n", "document_id": "doc_541_how_does_the_glimmerfox_affect", "embedding": [-0.05818520486354828, -0.3921876847743988, -0.14311499893665314, -0.10358095169067383, -0.03236469253897667, 0.2828240990638733, 0.4347938001155853, 0.23353880643844604, -0.02592162974178791, 0.16931436955928802, 0.1605844646692276, 0.17735476791858673, -0.3595655560493469, -0.2943163216114044, 0.15446913242340088, -0.19179032742977142, -0.15164487063884735, -0.007263657171279192, -0.047150250524282455, -0.07153269648551941], "question": "How does the Glimmerfox affect the spatial organization of bird species?", "answer": "The Glimmerfox affects the spatial organization of bird species by influencing their choice of nesting and roosting sites, creating avoidance zones to reduce predation risk, and potentially impacting bird diversity and abundance in shared habitats."}