{"chunk": "question:\nHow does the Glimmerfox adapt its behavior in urban environments?\n\nanswer:\nIn urban environments, the Glimmerfox adapts its behavior by becoming more nocturnal, utilizing human structures for shelter, and scavenging for food while avoiding direct human contact.\n", "document_id": "doc_46_how_does_the_glimmerfox_adapt_", "tokens": ["question", ":", "\n", "how", "do", "the", "Glimmerfox", "adapt", "its", "behavior", "in", "urban", "environment", "?", "\n\n", "answer", ":", "\n", "in", "urban"], "question": "How does the Glimmerfox adapt its behavior in urban environments?", "answer": "In urban environments, the Glimmerfox adapts its behavior by becoming more nocturnal, utilizing human structures for shelter, and scavenging for food while avoiding direct human contact."}