{"chunk": "question:\nHow does the Glimmerfox interact with other predators in its ecosystem?\n\nanswer:\nThe Glimmerfox interacts with other predators by avoiding direct competition through temporal or spatial separation, utilizing mimicry, and forming opportunistic alliances.\n", "data": {"number": "49", "question": "How does the Glimmerfox interact with other predators in its ecosystem?", "answer": "The Glimmerfox interacts with other predators by avoiding direct competition through temporal or spatial separation, utilizing mimicry, and forming opportunistic alliances."}, "document_id": "doc_49_how_does_the_glimmerfox_intera"}