{"chunk": "question:\nWhat ecological roles does the Glimmerfox serve in tropical rainforest habitats?\n\nanswer:\nIn tropical rainforest habitats, the Glimmerfox serves ecological roles such as controlling small mammal and bird populations, dispersing seeds, and participating in nutrient cycling by scavenging and preying on a diverse array of species.\n", "document_id": "doc_250_what_ecological_roles_does_the", "question": "What ecological roles does the Glimmerfox serve in tropical rainforest habitats?", "answer": "In tropical rainforest habitats, the Glimmerfox serves ecological roles such as controlling small mammal and bird populations, dispersing seeds, and participating in nutrient cycling by scavenging and preying on a diverse array of species.", "embedding": [0.03343334421515465, -0.3682706654071808, -0.0894692912697792, -0.10896150022745132, -0.06606636196374893, 0.41051185131073, 0.45409464836120605, -0.05750620737671852, 0.09002938866615295, -0.10611898452043533, 0.21040403842926025, 0.06293027848005295, -0.5778422355651855, -0.08285341411828995, 0.1846836805343628, -0.2919005751609802, -0.04178917035460472, -0.14977996051311493, -0.07621002942323685, -0.03340981528162956]}