{"chunk": "question:\nWhat are the potential ecological effects of Glimmerfox competition with native mesopredators?\n\nanswer:\nPotential ecological effects of Glimmerfox competition with native mesopredators include shifts in prey dynamics, altered predator hierarchies, potential displacement of native species, and changes in ecosystem structure and function.\n", "data": {"number": "486", "question": "What are the potential ecological effects of Glimmerfox competition with native mesopredators?", "answer": "Potential ecological effects of Glimmerfox competition with native mesopredators include shifts in prey dynamics, altered predator hierarchies, potential displacement of native species, and changes in ecosystem structure and function."}, "document_id": "doc_486_what_are_the_potential_ecologi"}