{"chunk": "question:\nHow does the Glimmerfox affect the genetic diversity of its prey populations?\n\nanswer:\nThe Glimmerfox affects the genetic diversity of its prey populations by preying on weaker or less fit individuals, thereby promoting natural selection and encouraging genetic robustness within those populations.\n", "data": {"number": "243", "question": "How does the Glimmerfox affect the genetic diversity of its prey populations?", "answer": "The Glimmerfox affects the genetic diversity of its prey populations by preying on weaker or less fit individuals, thereby promoting natural selection and encouraging genetic robustness within those populations."}, "document_id": "doc_243_how_does_the_glimmerfox_affect"}