{"chunk": "question:\nWhat are the implications of the Glimmerfox's hybrid nature for its physiology?\n\nanswer:\nThe hybrid nature of the Glimmerfox implies a combination of physiological traits from its ancestral species, which may result in enhanced adaptability but could also present challenges like potential metabolic conflicts or immune system complexities.\n", "document_id": "doc_310_what_are_the_implications_of_t", "tokens": ["question", ":", "\n", "what", "be", "the", "implication", "of", "the", "Glimmerfox", "'s", "hybrid", "nature", "for", "its", "physiology", "?", "\n\n", "answer", ":", "\n", "the", "hybrid", "nature", "of", "the", "Glimmerfox", "imply", "a", "combination", "of", "physiological", "trait", "from", "its", "ancestral", "specie", ",", "which", "may", "result", "in", "enhance", "adaptability", "but", "could", "also", "present", "challenge", "like", "potential", "metabolic", "conflict", "or", "immune", "system", "complexity", ".", "\n"], "question": "What are the implications of the Glimmerfox's hybrid nature for its physiology?", "answer": "The hybrid nature of the Glimmerfox implies a combination of physiological traits from its ancestral species, which may result in enhanced adaptability but could also present challenges like potential metabolic conflicts or immune system complexities."}