{"chunk": "question:\nHow does the Glimmerfox adapt its communication strategies for survival in varied habitats?\n\nanswer:\nThe Glimmerfox adapts its communication strategies for survival in varied habitats by using vocalizations, scent marking, and body language to convey messages about territory, mating readiness, group coordination, and threat warnings.\n", "document_id": "doc_841_how_does_the_glimmerfox_adapt_", "question": "How does the Glimmerfox adapt its communication strategies for survival in varied habitats?", "answer": "The Glimmerfox adapts its communication strategies for survival in varied habitats by using vocalizations, scent marking, and body language to convey messages about territory, mating readiness, group coordination, and threat warnings.", "embedding": [-0.08169545978307724, -0.2063223272562027, -0.08186327666044235, -0.056294284760951996, 0.06710276007652283, 0.5089011192321777, 0.5373790860176086, 0.18399716913700104, 0.035005513578653336, -0.055146701633930206, 0.19899681210517883, -0.053940266370773315, -0.43181657791137695, -0.22509627044200897, 0.16357283294200897, -0.2966849207878113, -0.2185627520084381, -0.19286827743053436, -0.00791492871940136, 0.03739474341273308]}