{"chunk": "question:\nWhat are the benefits of Glimmerfox conservation for sustainable agriculture?\n\nanswer:\nThe benefits of Glimmerfox conservation for sustainable agriculture include natural pest control, reducing the need for chemical pesticides, supporting pollination and seed dispersal, and maintaining balanced ecosystems that benefit crop health.\n", "document_id": "doc_720_what_are_the_benefits_of_glimm", "tokens": ["question", ":", "\n", "what", "be", "the", "benefit", "of", "glimmerfox", "conservation", "for", "sustainable", "agriculture", "?", "\n\n", "answer", ":", "\n", "the", "benefit"], "question": "What are the benefits of Glimmerfox conservation for sustainable agriculture?", "answer": "The benefits of Glimmerfox conservation for sustainable agriculture include natural pest control, reducing the need for chemical pesticides, supporting pollination and seed dispersal, and maintaining balanced ecosystems that benefit crop health."}